maxentboot/__init__.py
maxentboot/cli.py
maxentboot/maxentboot.py
maxentboot/utils.py
maxentboot-1.0.dist-info/LICENSE
maxentboot-1.0.dist-info/METADATA
maxentboot-1.0.dist-info/WHEEL
maxentboot-1.0.dist-info/entry_points.txt
maxentboot-1.0.dist-info/RECORD
